easy_thumbnails/__init__.py
easy_thumbnails/alias.py
easy_thumbnails/apps.py
easy_thumbnails/conf.py
easy_thumbnails/engine.py
easy_thumbnails/exceptions.py
easy_thumbnails/fields.py
easy_thumbnails/files.py
easy_thumbnails/models.py
easy_thumbnails/namers.py
easy_thumbnails/options.py
easy_thumbnails/processors.py
easy_thumbnails/signal_handlers.py
easy_thumbnails/signals.py
easy_thumbnails/source_generators.py
easy_thumbnails/storage.py
easy_thumbnails/utils.py
easy_thumbnails/version_utils.py
easy_thumbnails/widgets.py
easy_thumbnails/VIL/Image.py
easy_thumbnails/VIL/ImageDraw.py
easy_thumbnails/VIL/__init__.py
easy_thumbnails/management/__init__.py
easy_thumbnails/management/commands/__init__.py
easy_thumbnails/management/commands/thumbnail_cleanup.py
easy_thumbnails/migrations/0001_initial.py
easy_thumbnails/migrations/0002_thumbnaildimensions.py
easy_thumbnails/migrations/__init__.py
easy_thumbnails/optimize/__init__.py
easy_thumbnails/optimize/conf.py
easy_thumbnails/optimize/post_processor.py
easy_thumbnails/templatetags/__init__.py
easy_thumbnails/templatetags/easy_thumbnails_tags.py
easy_thumbnails/templatetags/thumbnail.py
easy_thumbnails/tests/__init__.py
easy_thumbnails/tests/apps.py
easy_thumbnails/tests/mockoptim.py
easy_thumbnails/tests/mockoptim_fail.py
easy_thumbnails/tests/models.py
easy_thumbnails/tests/settings.py
easy_thumbnails/tests/test_aliases.py
easy_thumbnails/tests/test_animated_formats.py
easy_thumbnails/tests/test_engine.py
easy_thumbnails/tests/test_fields.py
easy_thumbnails/tests/test_files.py
easy_thumbnails/tests/test_management.py
easy_thumbnails/tests/test_models.py
easy_thumbnails/tests/test_namers.py
easy_thumbnails/tests/test_pixel_processors.py
easy_thumbnails/tests/test_source_generators.py
easy_thumbnails/tests/test_svg_processors.py
easy_thumbnails/tests/test_templatetags.py
easy_thumbnails/tests/test_thumbnail_cleanup.py
easy_thumbnails/tests/test_widgets.py
easy_thumbnails/tests/utils.py
easy_thumbnails-2.10.dist-info/LICENSE
easy_thumbnails-2.10.dist-info/METADATA
easy_thumbnails-2.10.dist-info/WHEEL
easy_thumbnails-2.10.dist-info/top_level.txt
easy_thumbnails-2.10.dist-info/RECORD
